map_nl/__init__.py
map_nl/foo.py
map_nl/geojson/getter.py
map_nl/geojson/simplifier.py
map_nl/map/__init__.py
map_nl/map/base.py
map_nl/map/choropleth.py
map_nl/map/map.py
map_nl/utils/file_downloader.py
map_nl/utils/file_unizpper.py
map_nl-0.1.0.dist-info/LICENSE
map_nl-0.1.0.dist-info/METADATA
map_nl-0.1.0.dist-info/WHEEL
map_nl-0.1.0.dist-info/RECORD
